AUTHORS
CHANGES
LICENSE
MANIFEST.in
README
VERSION
requirements.txt
setup.py
proxyip/__init__.py
proxyip/data.py
proxyip/mix.py
proxyip/scan.py
proxyip/v2/__init__.py
proxyip/v2/cache.py
proxyip/v2/crawler.py
proxyip/v2/data.py
proxyip/v2/ping.py
python_proxyip.egg-info/PKG-INFO
python_proxyip.egg-info/SOURCES.txt
python_proxyip.egg-info/dependency_links.txt
python_proxyip.egg-info/pbr.json
python_proxyip.egg-info/requires.txt
python_proxyip.egg-info/top_level.txt