Metadata-Version: 1.0
Name: python-proxyip
Version: 1.1
Summary: python-proxyip
Home-page: https://github.com/lvjiyong/
Author: lvjiyong
Author-email: lvjiyong@gmail.com
License: GPL
Platform: any
